Chan_Theory/Market_Fractal.py
Chan_Theory/__init__.py
chan_theory-0.1.1.dist-info/licenses/LICENSE
chan_theory-0.1.1.dist-info/METADATA
chan_theory-0.1.1.dist-info/WHEEL
chan_theory-0.1.1.dist-info/top_level.txt
chan_theory-0.1.1.dist-info/RECORD
