Metadata-Version: 2.4
Name: Chan-Theory
Version: 0.1.1
Summary: This Package implements K-line data processing based on the Chan Theory.
Author-email: Yuhao Lian <lianyuhao@ieee.org>
License: GNU GENERAL PUBLIC LICENSE
Project-URL: Homepage, https://github.com/YuhaoLian/Chan-Theory
Keywords: Chan Theory,K-line
Classifier: License :: OSI Approved :: GNU General Public License v3 (GPLv3)
Classifier: Programming Language :: Python :: 3
Classifier: Programming Language :: Python :: 3.7
Requires-Python: >=3.7
License-File: LICENSE
Requires-Dist: requests
Requires-Dist: numpy>=1.18
Requires-Dist: pandas>=1.5.0
Dynamic: license-file
